Metadata-Version: 2.1
Name: nonebot-plugin-hitokoto
Version: 0.2.1
Summary: One sentence a day in Nonebot2
License: MIT
Author-email: Akirami <Akiramiaya@outlook.com>
Requires-Python: >=3.8
Requires-Dist: httpx>=0.23.1
Requires-Dist: nonebot-adapter-onebot>=2.0.0b1
Requires-Dist: nonebot2>=2.0.0b2
Project-URL: Homepage, https://github.com/A-kirami/nonebot-plugin-hitokoto
Project-URL: Repository, https://github.com/A-kirami/nonebot-plugin-hitokoto
